CyEulerBallistic/__init__.py
CyEulerBallistic/cy_euler.c
CyEulerBallistic/cy_euler.cp311-win_amd64.pyd
CyEulerBallistic/interface.py
CyEulerBallistic/trajectory_calc.c
CyEulerBallistic/trajectory_calc.cp311-win_amd64.pyd
CyEulerBallistic/trajectory_calc.pyi
CyEulerBallistic/trajectory_data.c
CyEulerBallistic/trajectory_data.cp311-win_amd64.pyd
CyEulerBallistic/trajectory_data.pyi
CyEulerBallistic/vector.c
CyEulerBallistic/vector.cp311-win_amd64.pyd
CyEulerBallistic/vector.pyi
cyeulerballistic-2.1.1b1.dist-info/licenses/LICENSE
cyeulerballistic-2.1.1b1.dist-info/METADATA
cyeulerballistic-2.1.1b1.dist-info/WHEEL
cyeulerballistic-2.1.1b1.dist-info/entry_points.txt
cyeulerballistic-2.1.1b1.dist-info/top_level.txt
cyeulerballistic-2.1.1b1.dist-info/RECORD
