Metadata-Version: 2.4
Name: CyEulerBallistic
Version: 2.1.1b1
Summary: LGPL library for small arms ballistic calculations (Python 3)
Author-email: o-murphy <thehelixpg@gmail.com>, dbookstaber <bookstaber@gmail.com>
License:                    GNU LESSER GENERAL PUBLIC LICENSE
Project-URL: Homepage, https://github.com/o-murphy/CyEulerBallistic
Project-URL: Bug Reports, https://github.com/o-murphy/CyEulerBallistic/issues
Project-URL: Source, https://github.com/o-murphy/CyEulerBallistic
Keywords: py_ballisticcalc,ballistics,Cython,ballistic calculator,python,python3
Classifier: Intended Audience :: Developers
Classifier: Natural Language :: English
Classifier: Programming Language :: Python
Classifier: Topic :: Software Development :: Libraries :: Python Modules
Classifier: Programming Language :: Python :: 3
Classifier: Programming Language :: Python :: 3 :: Only
Classifier: Programming Language :: Python :: 3.9
Classifier: Programming Language :: Python :: 3.10
Classifier: Programming Language :: Python :: 3.11
Classifier: Programming Language :: Python :: 3.12
Classifier: Operating System :: OS Independent
Classifier: Programming Language :: Python :: Implementation :: CPython
Requires-Python: >=3.9
License-File: LICENSE
Requires-Dist: py_ballisticcalc==2.1.1b1
Provides-Extra: dev
Requires-Dist: cython; extra == "dev"
Requires-Dist: build; extra == "dev"
Requires-Dist: setuptools; extra == "dev"
Requires-Dist: cibuildwheel; extra == "dev"
Requires-Dist: pytest; extra == "dev"
Dynamic: license-file
